{
  "drops": {
    "Group_1": {
      "exist": 1,
      "count": 1,
      "count_leader": "0d45db84-9179-4b23-93b7-38a90642b372",
      "max_weight": 0.0,
      "max_weight_leader": "0d45db84-9179-4b23-93b7-38a90642b372",
      "min_weight": 0.0,
      "min_weight_leader": "0d45db84-9179-4b23-93b7-38a90642b372",
      "sum_weight": 0.0
    },
    "Group_2": {
      "exist": 1,
      "count": 1,
      "count_leader": "0d45db84-9179-4b23-93b7-38a90642b372",
      "max_weight": 0.0,
      "max_weight_leader": "0d45db84-9179-4b23-93b7-38a90642b372",
      "min_weight": 0.0,
      "min_weight_leader": "0d45db84-9179-4b23-93b7-38a90642b372",
      "sum_weight": 0.0
    }
  },
  "max_weight_top": [],
  "min_weight_top": [],
  "count_top": [],
  "catch_top": [
    {
      "owner": "0d45db84-9179-4b23-93b7-38a90642b372",
      "amount": 2.0
    }
  ]
}